speechflow/__init__.py
speechflow/_version.py
speechflow/audio/__init__.py
speechflow/audio/player.py
speechflow/audio/writer.py
speechflow/core/__init__.py
speechflow/core/base.py
speechflow/core/exceptions.py
speechflow/engines/__init__.py
speechflow/engines/fishaudio.py
speechflow/engines/fishspeech.py
speechflow/engines/gemini.py
speechflow/engines/kokoro.py
speechflow/engines/openai.py
speechflow/engines/stylebert.py
speechflow-0.1.7.dist-info/METADATA
speechflow-0.1.7.dist-info/WHEEL
speechflow-0.1.7.dist-info/licenses/LICENSE
speechflow-0.1.7.dist-info/RECORD
