Metadata-Version: 2.4
Name: speechflow
Version: 0.1.7
Summary: TTS (Text-to-Speech) wrapper library for Python
Author-email: minamik <mia@sync.dev>
License-Expression: MIT
License-File: LICENSE
Keywords: fishaudio,gemini,kokoro,openai,speech-synthesis,style-bert-vits2,text-to-speech,tts
Classifier: Development Status :: 3 - Alpha
Classifier: Intended Audience :: Developers
Classifier: License :: OSI Approved :: MIT License
Classifier: Programming Language :: Python :: 3
Classifier: Programming Language :: Python :: 3.10
Classifier: Programming Language :: Python :: 3.11
Classifier: Programming Language :: Python :: 3.12
Classifier: Topic :: Multimedia :: Sound/Audio :: Speech
Classifier: Topic :: Software Development :: Libraries :: Python Modules
Requires-Python: >=3.10
Requires-Dist: fish-audio-sdk>=2025.6.3
Requires-Dist: google-genai>=1.18.0
Requires-Dist: kokoro>=0.9.4
Requires-Dist: misaki[ja]>=0.9.4
Requires-Dist: numba>=0.61
Requires-Dist: numpy>=1.26.4
Requires-Dist: openai>=1.84.0
Requires-Dist: pip>=25.2
Requires-Dist: pyaudio>=0.2.14
Requires-Dist: pydantic>=2.0
Requires-Dist: pyopenjtalk>=0.4.1
Requires-Dist: python-dotenv>=1.1.1
Requires-Dist: style-bert-vits2>=2.5.0
Requires-Dist: torch
Requires-Dist: torchaudio
Requires-Dist: torchvision
